COPYING
MANIFEST.in
README
py4s_helpers.c
setup.cfg
setup.py
py4s/__init__.py
py4s.egg-info/PKG-INFO
py4s.egg-info/SOURCES.txt
py4s.egg-info/dependency_links.txt
py4s.egg-info/entry_points.txt
py4s.egg-info/not-zip-safe
py4s.egg-info/requires.txt
py4s.egg-info/top_level.txt
tests/test_4store.py