Metadata-Version: 1.0
Name: py4s
Version: 0.2dev
Summary: Python C bindings for 4store
Home-page: http://github.com/wwaites/py4s
Author: William Waites
Author-email: wwaites_at_gmail.com
License: GPL
Keywords: 4store rdf triplestore
Platform: UNKNOWN
